[
  {
    "name": "Oats",
    "price": 16,
    "unit": "kg",
    "weight": "1 kg",
    "popular": true,
    "image": "pictures/tinified/lukasz-rawa-HB_MVtHVMLc-unsplash.jpg"
  },
  {
    "name": "Red onions",
    "price": 45,
    "unit": "kg",
    "weight": "1 kg",
    "popular": true,
    "image": "pictures/tinified/goh-rhy-yan-CCxWLAx0qmk-unsplash.jpg"
  },
  {
    "name": "Garlic",
    "price": 38,
    "unit": "kg",
    "weight": "0.2 kg",
    "popular": true,
    "image": "pictures/tinified/matthew-pilachowski-w1eAFyBLhLM-unsplash.jpg"
  },
  {
    "name": "Potatoes",
    "price": 20,
    "unit": "kg",
    "weight": "1 kg",
    "popular": false,
    "image": "pictures/tinified/rodrigo-dos-reis-h3AkzboxK4Q-unsplash.jpg"
  },
  {
    "name": "Carrots",
    "price": 25,
    "unit": "kg",
    "weight": "1 kg",
    "popular": false,
    "image": "pictures/tinified/goh-rhy-yan-wUBhu3GXIg0-unsplash.jpg"
  }
]
